[
	{
		"rank": "1",
		"img": "https://opgg-static.akamaized.net/meta/images/lol/champion/Zed.png?image=c_crop,h_103,w_103,x_9,y_9/q_auto,f_png,w_64&v=1669867001194",
		"name": "제드",
		"tier": "1",
		"win": "52.96%",
		"pick": "12.48%",
		"ben": "35.63%",
		"hard": [
			"https://opgg-static.akamaized.net/meta/images/lol/champion/Singed.png?image=c_crop,h_103,w_103,x_9,y_9/q_auto,f_png,w_48&v=1669867001194",
			"https://opgg-static.akamaized.net/meta/images/lol/champion/Tryndamere.png?image=c_crop,h_103,w_103,x_9,y_9/q_auto,f_png,w_48&v=1669867001194",
			"https://opgg-static.akamaized.net/meta/images/lol/champion/Rumble.png?image=c_crop,h_103,w_103,x_9,y_9/q_auto,f_png,w_48&v=1669867001194"
		]
	},
	{
		"rank": "2",
		"img": "https://opgg-static.akamaized.net/meta/images/lol/champion/Syndra.png?image=c_crop,h_103,w_103,x_9,y_9/q_auto,f_png,w_64&v=1669867001194",
		"name": "신드라",
		"tier": "1",
		"win": "51.60%",
		"pick": "10.64%",
		"ben": "11.12%",
		"hard": [
			"https://opgg-static.akamaized.net/meta/images/lol/champion/Singed.png?image=c_crop,h_103,w_103,x_9,y_9/q_auto,f_png,w_48&v=1669867001194",
			"https://opgg-static.akamaized.net/meta/images/lol/champion/Brand.png?image=c_crop,h_103,w_103,x_9,y_9/q_auto,f_png,w_48&v=1669867001194",
			"https://opgg-static.akamaized.net/meta/images/lol/champion/Zed.png?image=c_crop,h_103,w_103,x_9,y_9/q_auto,f_png,w_48&v=1669867001194"
		]
	},
	{
		"rank": "3",
		"img": "https://opgg-static.akamaized.net/meta/images/lol/champion/Vex.png?image=c_crop,h_103,w_103,x_9,y_9/q_auto,f_png,w_64&v=1669867001194",
		"name": "벡스",
		"tier": "2",
		"win": "51.84%",
		"pick": "5.26%",
		"ben": "10.60%",
		"hard": [
			"https://opgg-static.akamaized.net/meta/images/lol/champion/Tryndamere.png?image=c_crop,h_103,w_103,x_9,y_9/q_auto,f_png,w_48&v=1669867001194",
			"https://opgg-static.akamaized.net/meta/images/lol/champion/Rumble.png?image=c_crop,h_103,w_103,x_9,y_9/q_auto,f_png,w_48&v=1669867001194",
			"https://opgg-static.akamaized.net/meta/images/lol/champion/AurelionSol.png?image=c_crop,h_103,w_103,x_9,y_9/q_auto,f_png,w_48&v=1669867001194"
		]
	},
	{
		"rank": "4",
		"img": "https://opgg-static.akamaized.net/meta/images/lol/champion/Viktor.png?image=c_crop,h_103,w_103,x_9,y_9/q_auto,f_png,w_64&v=1669867001194",
		"name": "빅토르",
		"tier": "2",
		"win": "50.72%",
		"pick": "8.35%",
		"ben": "6.16%",
		"hard": [
			"https://opgg-static.akamaized.net/meta/images/lol/champion/Twitch.png?image=c_crop,h_103,w_103,x_9,y_9/q_auto,f_png,w_48&v=1669867001194",
			"https://opgg-static.akamaized.net/meta/images/lol/champion/Tryndamere.png?image=c_crop,h_103,w_103,x_9,y_9/q_auto,f_png,w_48&v=1669867001194",
			"https://opgg-static.akamaized.net/meta/images/lol/champion/Rumble.png?image=c_crop,h_103,w_103,x_9,y_9/q_auto,f_png,w_48&v=1669867001194"
		]
	},
	{
		"rank": "5",
		"img": "https://opgg-static.akamaized.net/meta/images/lol/champion/Singed.png?image=c_crop,h_103,w_103,x_9,y_9/q_auto,f_png,w_64&v=1669867001194",
		"name": "신지드",
		"tier": "2",
		"win": "55.17%",
		"pick": "0.69%",
		"ben": "0.11%",
		"hard": [
			"https://opgg-static.akamaized.net/meta/images/lol/champion/Gangplank.png?image=c_crop,h_103,w_103,x_9,y_9/q_auto,f_png,w_48&v=1669867001194",
			"https://opgg-static.akamaized.net/meta/images/lol/champion/TwistedFate.png?image=c_crop,h_103,w_103,x_9,y_9/q_auto,f_png,w_48&v=1669867001194",
			"https://opgg-static.akamaized.net/meta/images/lol/champion/Swain.png?image=c_crop,h_103,w_103,x_9,y_9/q_auto,f_png,w_48&v=1669867001194"
		]
	},
	{
		"rank": "6",
		"img": "https://opgg-static.akamaized.net/meta/images/lol/champion/Sylas.png?image=c_crop,h_103,w_103,x_9,y_9/q_auto,f_png,w_64&v=1669867001194",
		"name": "사일러스",
		"tier": "2",
		"win": "49.20%",
		"pick": "11.76%",
		"ben": "8.09%",
		"hard": [
			"https://opgg-static.akamaized.net/meta/images/lol/champion/Singed.png?image=c_crop,h_103,w_103,x_9,y_9/q_auto,f_png,w_48&v=1669867001194",
			"https://opgg-static.akamaized.net/meta/images/lol/champion/Heimerdinger.png?image=c_crop,h_103,w_103,x_9,y_9/q_auto,f_png,w_48&v=1669867001194",
			"https://opgg-static.akamaized.net/meta/images/lol/champion/Tryndamere.png?image=c_crop,h_103,w_103,x_9,y_9/q_auto,f_png,w_48&v=1669867001194"
		]
	},
	{
		"rank": "7",
		"img": "https://opgg-static.akamaized.net/meta/images/lol/champion/Anivia.png?image=c_crop,h_103,w_103,x_9,y_9/q_auto,f_png,w_64&v=1669867001194",
		"name": "애니비아",
		"tier": "2",
		"win": "52.16%",
		"pick": "2.62%",
		"ben": "2.17%",
		"hard": [
			"https://opgg-static.akamaized.net/meta/images/lol/champion/Brand.png?image=c_crop,h_103,w_103,x_9,y_9/q_auto,f_png,w_48&v=1669867001194",
			"https://opgg-static.akamaized.net/meta/images/lol/champion/Ziggs.png?image=c_crop,h_103,w_103,x_9,y_9/q_auto,f_png,w_48&v=1669867001194",
			"https://opgg-static.akamaized.net/meta/images/lol/champion/Corki.png?image=c_crop,h_103,w_103,x_9,y_9/q_auto,f_png,w_48&v=1669867001194"
		]
	},
	{
		"rank": "8",
		"img": "https://opgg-static.akamaized.net/meta/images/lol/champion/Pantheon.png?image=c_crop,h_103,w_103,x_9,y_9/q_auto,f_png,w_64&v=1669867001194",
		"name": "판테온",
		"tier": "3",
		"win": "53.58%",
		"pick": "1.15%",
		"ben": "0.17%",
		"hard": [
			"https://opgg-static.akamaized.net/meta/images/lol/champion/Malphite.png?image=c_crop,h_103,w_103,x_9,y_9/q_auto,f_png,w_48&v=1669867001194",
			"https://opgg-static.akamaized.net/meta/images/lol/champion/Veigar.png?image=c_crop,h_103,w_103,x_9,y_9/q_auto,f_png,w_48&v=1669867001194",
			"https://opgg-static.akamaized.net/meta/images/lol/champion/Diana.png?image=c_crop,h_103,w_103,x_9,y_9/q_auto,f_png,w_48&v=1669867001194"
		]
	},
	{
		"rank": "9",
		"img": "https://opgg-static.akamaized.net/meta/images/lol/champion/Irelia.png?image=c_crop,h_103,w_103,x_9,y_9/q_auto,f_png,w_64&v=1669867001194",
		"name": "이렐리아",
		"tier": "3",
		"win": "50.12%",
		"pick": "5.52%",
		"ben": "7.41%",
		"hard": [
			"https://opgg-static.akamaized.net/meta/images/lol/champion/Singed.png?image=c_crop,h_103,w_103,x_9,y_9/q_auto,f_png,w_48&v=1669867001194",
			"https://opgg-static.akamaized.net/meta/images/lol/champion/Pantheon.png?image=c_crop,h_103,w_103,x_9,y_9/q_auto,f_png,w_48&v=1669867001194",
			"https://opgg-static.akamaized.net/meta/images/lol/champion/Garen.png?image=c_crop,h_103,w_103,x_9,y_9/q_auto,f_png,w_48&v=1669867001194"
		]
	},
	{
		"rank": "10",
		"img": "https://opgg-static.akamaized.net/meta/images/lol/champion/Malzahar.png?image=c_crop,h_103,w_103,x_9,y_9/q_auto,f_png,w_64&v=1669867001194",
		"name": "말자하",
		"tier": "3",
		"win": "50.95%",
		"pick": "3.80%",
		"ben": "2.77%",
		"hard": [
			"https://opgg-static.akamaized.net/meta/images/lol/champion/Singed.png?image=c_crop,h_103,w_103,x_9,y_9/q_auto,f_png,w_48&v=1669867001194",
			"https://opgg-static.akamaized.net/meta/images/lol/champion/Tryndamere.png?image=c_crop,h_103,w_103,x_9,y_9/q_auto,f_png,w_48&v=1669867001194",
			"https://opgg-static.akamaized.net/meta/images/lol/champion/Taliyah.png?image=c_crop,h_103,w_103,x_9,y_9/q_auto,f_png,w_48&v=1669867001194"
		]
	},
	{
		"rank": "11",
		"img": "https://opgg-static.akamaized.net/meta/images/lol/champion/Yone.png?image=c_crop,h_103,w_103,x_9,y_9/q_auto,f_png,w_64&v=1669867001194",
		"name": "요네",
		"tier": "3",
		"win": "49.14%",
		"pick": "8.45%",
		"ben": "6.84%",
		"hard": [
			"https://opgg-static.akamaized.net/meta/images/lol/champion/Singed.png?image=c_crop,h_103,w_103,x_9,y_9/q_auto,f_png,w_48&v=1669867001194",
			"https://opgg-static.akamaized.net/meta/images/lol/champion/Sett.png?image=c_crop,h_103,w_103,x_9,y_9/q_auto,f_png,w_48&v=1669867001194",
			"https://opgg-static.akamaized.net/meta/images/lol/champion/Pantheon.png?image=c_crop,h_103,w_103,x_9,y_9/q_auto,f_png,w_48&v=1669867001194"
		]
	},
	{
		"rank": "12",
		"img": "https://opgg-static.akamaized.net/meta/images/lol/champion/Akshan.png?image=c_crop,h_103,w_103,x_9,y_9/q_auto,f_png,w_64&v=1669867001194",
		"name": "아크샨",
		"tier": "3",
		"win": "51.86%",
		"pick": "2.21%",
		"ben": "2.72%",
		"hard": [
			"https://opgg-static.akamaized.net/meta/images/lol/champion/Garen.png?image=c_crop,h_103,w_103,x_9,y_9/q_auto,f_png,w_48&v=1669867001194",
			"https://opgg-static.akamaized.net/meta/images/lol/champion/Pantheon.png?image=c_crop,h_103,w_103,x_9,y_9/q_auto,f_png,w_48&v=1669867001194",
			"https://opgg-static.akamaized.net/meta/images/lol/champion/Sett.png?image=c_crop,h_103,w_103,x_9,y_9/q_auto,f_png,w_48&v=1669867001194"
		]
	},
	{
		"rank": "13",
		"img": "https://opgg-static.akamaized.net/meta/images/lol/champion/Talon.png?image=c_crop,h_103,w_103,x_9,y_9/q_auto,f_png,w_64&v=1669867001194",
		"name": "탈론",
		"tier": "3",
		"win": "50.86%",
		"pick": "3.71%",
		"ben": "1.13%",
		"hard": [
			"https://opgg-static.akamaized.net/meta/images/lol/champion/Gragas.png?image=c_crop,h_103,w_103,x_9,y_9/q_auto,f_png,w_48&v=1669867001194",
			"https://opgg-static.akamaized.net/meta/images/lol/champion/Velkoz.png?image=c_crop,h_103,w_103,x_9,y_9/q_auto,f_png,w_48&v=1669867001194",
			"https://opgg-static.akamaized.net/meta/images/lol/champion/Zed.png?image=c_crop,h_103,w_103,x_9,y_9/q_auto,f_png,w_48&v=1669867001194"
		]
	},
	{
		"rank": "14",
		"img": "https://opgg-static.akamaized.net/meta/images/lol/champion/Kassadin.png?image=c_crop,h_103,w_103,x_9,y_9/q_auto,f_png,w_64&v=1669867001194",
		"name": "카사딘",
		"tier": "3",
		"win": "49.68%",
		"pick": "6.47%",
		"ben": "9.03%",
		"hard": [
			"https://opgg-static.akamaized.net/meta/images/lol/champion/Akshan.png?image=c_crop,h_103,w_103,x_9,y_9/q_auto,f_png,w_48&v=1669867001194",
			"https://opgg-static.akamaized.net/meta/images/lol/champion/Gangplank.png?image=c_crop,h_103,w_103,x_9,y_9/q_auto,f_png,w_48&v=1669867001194",
			"https://opgg-static.akamaized.net/meta/images/lol/champion/Garen.png?image=c_crop,h_103,w_103,x_9,y_9/q_auto,f_png,w_48&v=1669867001194"
		]
	},
	{
		"rank": "15",
		"img": "https://opgg-static.akamaized.net/meta/images/lol/champion/Katarina.png?image=c_crop,h_103,w_103,x_9,y_9/q_auto,f_png,w_64&v=1669867001194",
		"name": "카타리나",
		"tier": "3",
		"win": "48.93%",
		"pick": "8.38%",
		"ben": "8.12%",
		"hard": [
			"https://opgg-static.akamaized.net/meta/images/lol/champion/Singed.png?image=c_crop,h_103,w_103,x_9,y_9/q_auto,f_png,w_48&v=1669867001194",
			"https://opgg-static.akamaized.net/meta/images/lol/champion/Tryndamere.png?image=c_crop,h_103,w_103,x_9,y_9/q_auto,f_png,w_48&v=1669867001194",
			"https://opgg-static.akamaized.net/meta/images/lol/champion/Heimerdinger.png?image=c_crop,h_103,w_103,x_9,y_9/q_auto,f_png,w_48&v=1669867001194"
		]
	},
	{
		"rank": "16",
		"img": "https://opgg-static.akamaized.net/meta/images/lol/champion/Akali.png?image=c_crop,h_103,w_103,x_9,y_9/q_auto,f_png,w_64&v=1669867001194",
		"name": "아칼리",
		"tier": "3",
		"win": "48.43%",
		"pick": "9.73%",
		"ben": "12.29%",
		"hard": [
			"https://opgg-static.akamaized.net/meta/images/lol/champion/Singed.png?image=c_crop,h_103,w_103,x_9,y_9/q_auto,f_png,w_48&v=1669867001194",
			"https://opgg-static.akamaized.net/meta/images/lol/champion/Pantheon.png?image=c_crop,h_103,w_103,x_9,y_9/q_auto,f_png,w_48&v=1669867001194",
			"https://opgg-static.akamaized.net/meta/images/lol/champion/Gangplank.png?image=c_crop,h_103,w_103,x_9,y_9/q_auto,f_png,w_48&v=1669867001194"
		]
	},
	{
		"rank": "17",
		"img": "https://opgg-static.akamaized.net/meta/images/lol/champion/Ahri.png?image=c_crop,h_103,w_103,x_9,y_9/q_auto,f_png,w_64&v=1669867001194",
		"name": "아리",
		"tier": "3",
		"win": "50.10%",
		"pick": "4.33%",
		"ben": "1.64%",
		"hard": [
			"https://opgg-static.akamaized.net/meta/images/lol/champion/Garen.png?image=c_crop,h_103,w_103,x_9,y_9/q_auto,f_png,w_48&v=1669867001194",
			"https://opgg-static.akamaized.net/meta/images/lol/champion/Sett.png?image=c_crop,h_103,w_103,x_9,y_9/q_auto,f_png,w_48&v=1669867001194",
			"https://opgg-static.akamaized.net/meta/images/lol/champion/Twitch.png?image=c_crop,h_103,w_103,x_9,y_9/q_auto,f_png,w_48&v=1669867001194"
		]
	},
	{
		"rank": "18",
		"img": "https://opgg-static.akamaized.net/meta/images/lol/champion/Rumble.png?image=c_crop,h_103,w_103,x_9,y_9/q_auto,f_png,w_64&v=1669867001194",
		"name": "럼블",
		"tier": "3",
		"win": "52.59%",
		"pick": "1.16%",
		"ben": "0.27%",
		"hard": [
			"https://opgg-static.akamaized.net/meta/images/lol/champion/Veigar.png?image=c_crop,h_103,w_103,x_9,y_9/q_auto,f_png,w_48&v=1669867001194",
			"https://opgg-static.akamaized.net/meta/images/lol/champion/Lissandra.png?image=c_crop,h_103,w_103,x_9,y_9/q_auto,f_png,w_48&v=1669867001194",
			"https://opgg-static.akamaized.net/meta/images/lol/champion/Pantheon.png?image=c_crop,h_103,w_103,x_9,y_9/q_auto,f_png,w_48&v=1669867001194"
		]
	},
	{
		"rank": "19",
		"img": "https://opgg-static.akamaized.net/meta/images/lol/champion/Fizz.png?image=c_crop,h_103,w_103,x_9,y_9/q_auto,f_png,w_64&v=1669867001194",
		"name": "피즈",
		"tier": "3",
		"win": "50.74%",
		"pick": "2.96%",
		"ben": "2.89%",
		"hard": [
			"https://opgg-static.akamaized.net/meta/images/lol/champion/Singed.png?image=c_crop,h_103,w_103,x_9,y_9/q_auto,f_png,w_48&v=1669867001194",
			"https://opgg-static.akamaized.net/meta/images/lol/champion/Pantheon.png?image=c_crop,h_103,w_103,x_9,y_9/q_auto,f_png,w_48&v=1669867001194",
			"https://opgg-static.akamaized.net/meta/images/lol/champion/Garen.png?image=c_crop,h_103,w_103,x_9,y_9/q_auto,f_png,w_48&v=1669867001194"
		]
	},
	{
		"rank": "20",
		"img": "https://opgg-static.akamaized.net/meta/images/lol/champion/Yasuo.png?image=c_crop,h_103,w_103,x_9,y_9/q_auto,f_png,w_64&v=1669867001194",
		"name": "야스오",
		"tier": "3",
		"win": "48.42%",
		"pick": "8.46%",
		"ben": "10.49%",
		"hard": [
			"https://opgg-static.akamaized.net/meta/images/lol/champion/Annie.png?image=c_crop,h_103,w_103,x_9,y_9/q_auto,f_png,w_48&v=1669867001194",
			"https://opgg-static.akamaized.net/meta/images/lol/champion/Pantheon.png?image=c_crop,h_103,w_103,x_9,y_9/q_auto,f_png,w_48&v=1669867001194",
			"https://opgg-static.akamaized.net/meta/images/lol/champion/Gangplank.png?image=c_crop,h_103,w_103,x_9,y_9/q_auto,f_png,w_48&v=1669867001194"
		]
	},
	{
		"rank": "21",
		"img": "https://opgg-static.akamaized.net/meta/images/lol/champion/Galio.png?image=c_crop,h_103,w_103,x_9,y_9/q_auto,f_png,w_64&v=1669867001194",
		"name": "갈리오",
		"tier": "4",
		"win": "51.29%",
		"pick": "1.85%",
		"ben": "0.25%",
		"hard": [
			"https://opgg-static.akamaized.net/meta/images/lol/champion/Garen.png?image=c_crop,h_103,w_103,x_9,y_9/q_auto,f_png,w_48&v=1669867001194",
			"https://opgg-static.akamaized.net/meta/images/lol/champion/Gangplank.png?image=c_crop,h_103,w_103,x_9,y_9/q_auto,f_png,w_48&v=1669867001194",
			"https://opgg-static.akamaized.net/meta/images/lol/champion/Brand.png?image=c_crop,h_103,w_103,x_9,y_9/q_auto,f_png,w_48&v=1669867001194"
		]
	},
	{
		"rank": "22",
		"img": "https://opgg-static.akamaized.net/meta/images/lol/champion/Lux.png?image=c_crop,h_103,w_103,x_9,y_9/q_auto,f_png,w_64&v=1669867001194",
		"name": "럭스",
		"tier": "4",
		"win": "50.39%",
		"pick": "2.68%",
		"ben": "0.62%",
		"hard": [
			"https://opgg-static.akamaized.net/meta/images/lol/champion/Pantheon.png?image=c_crop,h_103,w_103,x_9,y_9/q_auto,f_png,w_48&v=1669867001194",
			"https://opgg-static.akamaized.net/meta/images/lol/champion/Velkoz.png?image=c_crop,h_103,w_103,x_9,y_9/q_auto,f_png,w_48&v=1669867001194",
			"https://opgg-static.akamaized.net/meta/images/lol/champion/Chogath.png?image=c_crop,h_103,w_103,x_9,y_9/q_auto,f_png,w_48&v=1669867001194"
		]
	},
	{
		"rank": "23",
		"img": "https://opgg-static.akamaized.net/meta/images/lol/champion/Gangplank.png?image=c_crop,h_103,w_103,x_9,y_9/q_auto,f_png,w_64&v=1669867001194",
		"name": "갱플랭크",
		"tier": "4",
		"win": "51.46%",
		"pick": "1.48%",
		"ben": "0.97%",
		"hard": [
			"https://opgg-static.akamaized.net/meta/images/lol/champion/Tryndamere.png?image=c_crop,h_103,w_103,x_9,y_9/q_auto,f_png,w_48&v=1669867001194",
			"https://opgg-static.akamaized.net/meta/images/lol/champion/Twitch.png?image=c_crop,h_103,w_103,x_9,y_9/q_auto,f_png,w_48&v=1669867001194",
			"https://opgg-static.akamaized.net/meta/images/lol/champion/Xerath.png?image=c_crop,h_103,w_103,x_9,y_9/q_auto,f_png,w_48&v=1669867001194"
		]
	},
	{
		"rank": "24",
		"img": "https://opgg-static.akamaized.net/meta/images/lol/champion/Vladimir.png?image=c_crop,h_103,w_103,x_9,y_9/q_auto,f_png,w_64&v=1669867001194",
		"name": "블라디미르",
		"tier": "4",
		"win": "49.60%",
		"pick": "3.88%",
		"ben": "4.88%",
		"hard": [
			"https://opgg-static.akamaized.net/meta/images/lol/champion/Renekton.png?image=c_crop,h_103,w_103,x_9,y_9/q_auto,f_png,w_48&v=1669867001194",
			"https://opgg-static.akamaized.net/meta/images/lol/champion/Anivia.png?image=c_crop,h_103,w_103,x_9,y_9/q_auto,f_png,w_48&v=1669867001194",
			"https://opgg-static.akamaized.net/meta/images/lol/champion/Pantheon.png?image=c_crop,h_103,w_103,x_9,y_9/q_auto,f_png,w_48&v=1669867001194"
		]
	},
	{
		"rank": "25",
		"img": "https://opgg-static.akamaized.net/meta/images/lol/champion/Ekko.png?image=c_crop,h_103,w_103,x_9,y_9/q_auto,f_png,w_64&v=1669867001194",
		"name": "에코",
		"tier": "4",
		"win": "50.10%",
		"pick": "2.53%",
		"ben": "2.01%",
		"hard": [
			"https://opgg-static.akamaized.net/meta/images/lol/champion/Garen.png?image=c_crop,h_103,w_103,x_9,y_9/q_auto,f_png,w_48&v=1669867001194",
			"https://opgg-static.akamaized.net/meta/images/lol/champion/Tryndamere.png?image=c_crop,h_103,w_103,x_9,y_9/q_auto,f_png,w_48&v=1669867001194",
			"https://opgg-static.akamaized.net/meta/images/lol/champion/Neeko.png?image=c_crop,h_103,w_103,x_9,y_9/q_auto,f_png,w_48&v=1669867001194"
		]
	},
	{
		"rank": "26",
		"img": "https://opgg-static.akamaized.net/meta/images/lol/champion/Heimerdinger.png?image=c_crop,h_103,w_103,x_9,y_9/q_auto,f_png,w_64&v=1669867001194",
		"name": "하이머딩거",
		"tier": "4",
		"win": "52.43%",
		"pick": "0.73%",
		"ben": "1.02%",
		"hard": [
			"https://opgg-static.akamaized.net/meta/images/lol/champion/Syndra.png?image=c_crop,h_103,w_103,x_9,y_9/q_auto,f_png,w_48&v=1669867001194",
			"https://opgg-static.akamaized.net/meta/images/lol/champion/Twitch.png?image=c_crop,h_103,w_103,x_9,y_9/q_auto,f_png,w_48&v=1669867001194",
			"https://opgg-static.akamaized.net/meta/images/lol/champion/Qiyana.png?image=c_crop,h_103,w_103,x_9,y_9/q_auto,f_png,w_48&v=1669867001194"
		]
	},
	{
		"rank": "27",
		"img": "https://opgg-static.akamaized.net/meta/images/lol/champion/Tryndamere.png?image=c_crop,h_103,w_103,x_9,y_9/q_auto,f_png,w_64&v=1669867001194",
		"name": "트린다미어",
		"tier": "4",
		"win": "52.76%",
		"pick": "0.66%",
		"ben": "0.45%",
		"hard": [
			"https://opgg-static.akamaized.net/meta/images/lol/champion/Singed.png?image=c_crop,h_103,w_103,x_9,y_9/q_auto,f_png,w_48&v=1669867001194",
			"https://opgg-static.akamaized.net/meta/images/lol/champion/Sett.png?image=c_crop,h_103,w_103,x_9,y_9/q_auto,f_png,w_48&v=1669867001194",
			"https://opgg-static.akamaized.net/meta/images/lol/champion/Velkoz.png?image=c_crop,h_103,w_103,x_9,y_9/q_auto,f_png,w_48&v=1669867001194"
		]
	},
	{
		"rank": "28",
		"img": "https://opgg-static.akamaized.net/meta/images/lol/champion/Swain.png?image=c_crop,h_103,w_103,x_9,y_9/q_auto,f_png,w_64&v=1669867001194",
		"name": "스웨인",
		"tier": "4",
		"win": "50.29%",
		"pick": "2.25%",
		"ben": "0.65%",
		"hard": [
			"https://opgg-static.akamaized.net/meta/images/lol/champion/Brand.png?image=c_crop,h_103,w_103,x_9,y_9/q_auto,f_png,w_48&v=1669867001194",
			"https://opgg-static.akamaized.net/meta/images/lol/champion/Tristana.png?image=c_crop,h_103,w_103,x_9,y_9/q_auto,f_png,w_48&v=1669867001194",
			"https://opgg-static.akamaized.net/meta/images/lol/champion/Pantheon.png?image=c_crop,h_103,w_103,x_9,y_9/q_auto,f_png,w_48&v=1669867001194"
		]
	},
	{
		"rank": "29",
		"img": "https://opgg-static.akamaized.net/meta/images/lol/champion/Twitch.png?image=c_crop,h_103,w_103,x_9,y_9/q_auto,f_png,w_64&v=1669867001194",
		"name": "트위치",
		"tier": "4",
		"win": "52.00%",
		"pick": "0.86%",
		"ben": "0.60%",
		"hard": [
			"https://opgg-static.akamaized.net/meta/images/lol/champion/Neeko.png?image=c_crop,h_103,w_103,x_9,y_9/q_auto,f_png,w_48&v=1669867001194",
			"https://opgg-static.akamaized.net/meta/images/lol/champion/Renekton.png?image=c_crop,h_103,w_103,x_9,y_9/q_auto,f_png,w_48&v=1669867001194",
			"https://opgg-static.akamaized.net/meta/images/lol/champion/Akshan.png?image=c_crop,h_103,w_103,x_9,y_9/q_auto,f_png,w_48&v=1669867001194"
		]
	},
	{
		"rank": "30",
		"img": "https://opgg-static.akamaized.net/meta/images/lol/champion/Velkoz.png?image=c_crop,h_103,w_103,x_9,y_9/q_auto,f_png,w_64&v=1669867001194",
		"name": "벨코즈",
		"tier": "4",
		"win": "51.97%",
		"pick": "0.96%",
		"ben": "0.10%",
		"hard": [
			"https://opgg-static.akamaized.net/meta/images/lol/champion/Annie.png?image=c_crop,h_103,w_103,x_9,y_9/q_auto,f_png,w_48&v=1669867001194",
			"https://opgg-static.akamaized.net/meta/images/lol/champion/Singed.png?image=c_crop,h_103,w_103,x_9,y_9/q_auto,f_png,w_48&v=1669867001194",
			"https://opgg-static.akamaized.net/meta/images/lol/champion/Akshan.png?image=c_crop,h_103,w_103,x_9,y_9/q_auto,f_png,w_48&v=1669867001194"
		]
	},
	{
		"rank": "31",
		"img": "https://opgg-static.akamaized.net/meta/images/lol/champion/Cassiopeia.png?image=c_crop,h_103,w_103,x_9,y_9/q_auto,f_png,w_64&v=1669867001194",
		"name": "카시오페아",
		"tier": "4",
		"win": "50.33%",
		"pick": "2.08%",
		"ben": "1.27%",
		"hard": [
			"https://opgg-static.akamaized.net/meta/images/lol/champion/Heimerdinger.png?image=c_crop,h_103,w_103,x_9,y_9/q_auto,f_png,w_48&v=1669867001194",
			"https://opgg-static.akamaized.net/meta/images/lol/champion/Renekton.png?image=c_crop,h_103,w_103,x_9,y_9/q_auto,f_png,w_48&v=1669867001194",
			"https://opgg-static.akamaized.net/meta/images/lol/champion/Neeko.png?image=c_crop,h_103,w_103,x_9,y_9/q_auto,f_png,w_48&v=1669867001194"
		]
	},
	{
		"rank": "32",
		"img": "https://opgg-static.akamaized.net/meta/images/lol/champion/Diana.png?image=c_crop,h_103,w_103,x_9,y_9/q_auto,f_png,w_64&v=1669867001194",
		"name": "다이애나",
		"tier": "4",
		"win": "50.36%",
		"pick": "1.65%",
		"ben": "1.09%",
		"hard": [
			"https://opgg-static.akamaized.net/meta/images/lol/champion/Malphite.png?image=c_crop,h_103,w_103,x_9,y_9/q_auto,f_png,w_48&v=1669867001194",
			"https://opgg-static.akamaized.net/meta/images/lol/champion/Heimerdinger.png?image=c_crop,h_103,w_103,x_9,y_9/q_auto,f_png,w_48&v=1669867001194",
			"https://opgg-static.akamaized.net/meta/images/lol/champion/Tryndamere.png?image=c_crop,h_103,w_103,x_9,y_9/q_auto,f_png,w_48&v=1669867001194"
		]
	},
	{
		"rank": "33",
		"img": "https://opgg-static.akamaized.net/meta/images/lol/champion/Qiyana.png?image=c_crop,h_103,w_103,x_9,y_9/q_auto,f_png,w_64&v=1669867001194",
		"name": "키아나",
		"tier": "4",
		"win": "49.52%",
		"pick": "2.59%",
		"ben": "0.73%",
		"hard": [
			"https://opgg-static.akamaized.net/meta/images/lol/champion/Pantheon.png?image=c_crop,h_103,w_103,x_9,y_9/q_auto,f_png,w_48&v=1669867001194",
			"https://opgg-static.akamaized.net/meta/images/lol/champion/Neeko.png?image=c_crop,h_103,w_103,x_9,y_9/q_auto,f_png,w_48&v=1669867001194",
			"https://opgg-static.akamaized.net/meta/images/lol/champion/Singed.png?image=c_crop,h_103,w_103,x_9,y_9/q_auto,f_png,w_48&v=1669867001194"
		]
	},
	{
		"rank": "34",
		"img": "https://opgg-static.akamaized.net/meta/images/lol/champion/Garen.png?image=c_crop,h_103,w_103,x_9,y_9/q_auto,f_png,w_64&v=1669867001194",
		"name": "가렌",
		"tier": "4",
		"win": "52.62%",
		"pick": "0.50%",
		"ben": "0.21%",
		"hard": [
			"https://opgg-static.akamaized.net/meta/images/lol/champion/Pantheon.png?image=c_crop,h_103,w_103,x_9,y_9/q_auto,f_png,w_48&v=1669867001194",
			"https://opgg-static.akamaized.net/meta/images/lol/champion/Tryndamere.png?image=c_crop,h_103,w_103,x_9,y_9/q_auto,f_png,w_48&v=1669867001194",
			"https://opgg-static.akamaized.net/meta/images/lol/champion/Malzahar.png?image=c_crop,h_103,w_103,x_9,y_9/q_auto,f_png,w_48&v=1669867001194"
		]
	},
	{
		"rank": "35",
		"img": "https://opgg-static.akamaized.net/meta/images/lol/champion/Veigar.png?image=c_crop,h_103,w_103,x_9,y_9/q_auto,f_png,w_64&v=1669867001194",
		"name": "베이가",
		"tier": "4",
		"win": "49.35%",
		"pick": "2.48%",
		"ben": "0.62%",
		"hard": [
			"https://opgg-static.akamaized.net/meta/images/lol/champion/Velkoz.png?image=c_crop,h_103,w_103,x_9,y_9/q_auto,f_png,w_48&v=1669867001194",
			"https://opgg-static.akamaized.net/meta/images/lol/champion/Gragas.png?image=c_crop,h_103,w_103,x_9,y_9/q_auto,f_png,w_48&v=1669867001194",
			"https://opgg-static.akamaized.net/meta/images/lol/champion/Zed.png?image=c_crop,h_103,w_103,x_9,y_9/q_auto,f_png,w_48&v=1669867001194"
		]
	},
	{
		"rank": "36",
		"img": "https://opgg-static.akamaized.net/meta/images/lol/champion/Zoe.png?image=c_crop,h_103,w_103,x_9,y_9/q_auto,f_png,w_64&v=1669867001194",
		"name": "조이",
		"tier": "4",
		"win": "49.57%",
		"pick": "2.19%",
		"ben": "0.83%",
		"hard": [
			"https://opgg-static.akamaized.net/meta/images/lol/champion/Singed.png?image=c_crop,h_103,w_103,x_9,y_9/q_auto,f_png,w_48&v=1669867001194",
			"https://opgg-static.akamaized.net/meta/images/lol/champion/Tristana.png?image=c_crop,h_103,w_103,x_9,y_9/q_auto,f_png,w_48&v=1669867001194",
			"https://opgg-static.akamaized.net/meta/images/lol/champion/Anivia.png?image=c_crop,h_103,w_103,x_9,y_9/q_auto,f_png,w_48&v=1669867001194"
		]
	},
	{
		"rank": "37",
		"img": "https://opgg-static.akamaized.net/meta/images/lol/champion/Tristana.png?image=c_crop,h_103,w_103,x_9,y_9/q_auto,f_png,w_64&v=1669867001194",
		"name": "트리스타나",
		"tier": "4",
		"win": "51.35%",
		"pick": "0.74%",
		"ben": "0.18%",
		"hard": [
			"https://opgg-static.akamaized.net/meta/images/lol/champion/Qiyana.png?image=c_crop,h_103,w_103,x_9,y_9/q_auto,f_png,w_48&v=1669867001194",
			"https://opgg-static.akamaized.net/meta/images/lol/champion/Twitch.png?image=c_crop,h_103,w_103,x_9,y_9/q_auto,f_png,w_48&v=1669867001194",
			"https://opgg-static.akamaized.net/meta/images/lol/champion/Gangplank.png?image=c_crop,h_103,w_103,x_9,y_9/q_auto,f_png,w_48&v=1669867001194"
		]
	},
	{
		"rank": "38",
		"img": "https://opgg-static.akamaized.net/meta/images/lol/champion/Xerath.png?image=c_crop,h_103,w_103,x_9,y_9/q_auto,f_png,w_64&v=1669867001194",
		"name": "제라스",
		"tier": "4",
		"win": "49.79%",
		"pick": "1.60%",
		"ben": "0.95%",
		"hard": [
			"https://opgg-static.akamaized.net/meta/images/lol/champion/Tryndamere.png?image=c_crop,h_103,w_103,x_9,y_9/q_auto,f_png,w_48&v=1669867001194",
			"https://opgg-static.akamaized.net/meta/images/lol/champion/Singed.png?image=c_crop,h_103,w_103,x_9,y_9/q_auto,f_png,w_48&v=1669867001194",
			"https://opgg-static.akamaized.net/meta/images/lol/champion/Akshan.png?image=c_crop,h_103,w_103,x_9,y_9/q_auto,f_png,w_48&v=1669867001194"
		]
	},
	{
		"rank": "39",
		"img": "https://opgg-static.akamaized.net/meta/images/lol/champion/Annie.png?image=c_crop,h_103,w_103,x_9,y_9/q_auto,f_png,w_64&v=1669867001194",
		"name": "애니",
		"tier": "4",
		"win": "50.57%",
		"pick": "1.01%",
		"ben": "0.24%",
		"hard": [
			"https://opgg-static.akamaized.net/meta/images/lol/champion/Singed.png?image=c_crop,h_103,w_103,x_9,y_9/q_auto,f_png,w_48&v=1669867001194",
			"https://opgg-static.akamaized.net/meta/images/lol/champion/Tryndamere.png?image=c_crop,h_103,w_103,x_9,y_9/q_auto,f_png,w_48&v=1669867001194",
			"https://opgg-static.akamaized.net/meta/images/lol/champion/Gragas.png?image=c_crop,h_103,w_103,x_9,y_9/q_auto,f_png,w_48&v=1669867001194"
		]
	},
	{
		"rank": "40",
		"img": "https://opgg-static.akamaized.net/meta/images/lol/champion/Neeko.png?image=c_crop,h_103,w_103,x_9,y_9/q_auto,f_png,w_64&v=1669867001194",
		"name": "니코",
		"tier": "4",
		"win": "51.15%",
		"pick": "0.73%",
		"ben": "0.17%",
		"hard": [
			"https://opgg-static.akamaized.net/meta/images/lol/champion/Gangplank.png?image=c_crop,h_103,w_103,x_9,y_9/q_auto,f_png,w_48&v=1669867001194",
			"https://opgg-static.akamaized.net/meta/images/lol/champion/Xerath.png?image=c_crop,h_103,w_103,x_9,y_9/q_auto,f_png,w_48&v=1669867001194",
			"https://opgg-static.akamaized.net/meta/images/lol/champion/Anivia.png?image=c_crop,h_103,w_103,x_9,y_9/q_auto,f_png,w_48&v=1669867001194"
		]
	},
	{
		"rank": "41",
		"img": "https://opgg-static.akamaized.net/meta/images/lol/champion/Lissandra.png?image=c_crop,h_103,w_103,x_9,y_9/q_auto,f_png,w_64&v=1669867001194",
		"name": "리산드라",
		"tier": "5",
		"win": "48.91%",
		"pick": "2.04%",
		"ben": "0.69%",
		"hard": [
			"https://opgg-static.akamaized.net/meta/images/lol/champion/Heimerdinger.png?image=c_crop,h_103,w_103,x_9,y_9/q_auto,f_png,w_48&v=1669867001194",
			"https://opgg-static.akamaized.net/meta/images/lol/champion/Pantheon.png?image=c_crop,h_103,w_103,x_9,y_9/q_auto,f_png,w_48&v=1669867001194",
			"https://opgg-static.akamaized.net/meta/images/lol/champion/Twitch.png?image=c_crop,h_103,w_103,x_9,y_9/q_auto,f_png,w_48&v=1669867001194"
		]
	},
	{
		"rank": "42",
		"img": "https://opgg-static.akamaized.net/meta/images/lol/champion/TwistedFate.png?image=c_crop,h_103,w_103,x_9,y_9/q_auto,f_png,w_64&v=1669867001194",
		"name": "트위스티드 페이트",
		"tier": "5",
		"win": "48.45%",
		"pick": "2.47%",
		"ben": "0.12%",
		"hard": [
			"https://opgg-static.akamaized.net/meta/images/lol/champion/Brand.png?image=c_crop,h_103,w_103,x_9,y_9/q_auto,f_png,w_48&v=1669867001194",
			"https://opgg-static.akamaized.net/meta/images/lol/champion/Sett.png?image=c_crop,h_103,w_103,x_9,y_9/q_auto,f_png,w_48&v=1669867001194",
			"https://opgg-static.akamaized.net/meta/images/lol/champion/Tryndamere.png?image=c_crop,h_103,w_103,x_9,y_9/q_auto,f_png,w_48&v=1669867001194"
		]
	},
	{
		"rank": "43",
		"img": "https://opgg-static.akamaized.net/meta/images/lol/champion/Sett.png?image=c_crop,h_103,w_103,x_9,y_9/q_auto,f_png,w_64&v=1669867001194",
		"name": "세트",
		"tier": "5",
		"win": "50.32%",
		"pick": "0.84%",
		"ben": "0.33%",
		"hard": [
			"https://opgg-static.akamaized.net/meta/images/lol/champion/Singed.png?image=c_crop,h_103,w_103,x_9,y_9/q_auto,f_png,w_48&v=1669867001194",
			"https://opgg-static.akamaized.net/meta/images/lol/champion/Annie.png?image=c_crop,h_103,w_103,x_9,y_9/q_auto,f_png,w_48&v=1669867001194",
			"https://opgg-static.akamaized.net/meta/images/lol/champion/Velkoz.png?image=c_crop,h_103,w_103,x_9,y_9/q_auto,f_png,w_48&v=1669867001194"
		]
	},
	{
		"rank": "44",
		"img": "https://opgg-static.akamaized.net/meta/images/lol/champion/Orianna.png?image=c_crop,h_103,w_103,x_9,y_9/q_auto,f_png,w_64&v=1669867001194",
		"name": "오리아나",
		"tier": "5",
		"win": "48.99%",
		"pick": "1.79%",
		"ben": "0.11%",
		"hard": [
			"https://opgg-static.akamaized.net/meta/images/lol/champion/Malphite.png?image=c_crop,h_103,w_103,x_9,y_9/q_auto,f_png,w_48&v=1669867001194",
			"https://opgg-static.akamaized.net/meta/images/lol/champion/Sett.png?image=c_crop,h_103,w_103,x_9,y_9/q_auto,f_png,w_48&v=1669867001194",
			"https://opgg-static.akamaized.net/meta/images/lol/champion/Jayce.png?image=c_crop,h_103,w_103,x_9,y_9/q_auto,f_png,w_48&v=1669867001194"
		]
	},
	{
		"rank": "45",
		"img": "https://opgg-static.akamaized.net/meta/images/lol/champion/Gragas.png?image=c_crop,h_103,w_103,x_9,y_9/q_auto,f_png,w_64&v=1669867001194",
		"name": "그라가스",
		"tier": "5",
		"win": "50.35%",
		"pick": "0.82%",
		"ben": "0.09%",
		"hard": [
			"https://opgg-static.akamaized.net/meta/images/lol/champion/Tristana.png?image=c_crop,h_103,w_103,x_9,y_9/q_auto,f_png,w_48&v=1669867001194",
			"https://opgg-static.akamaized.net/meta/images/lol/champion/Heimerdinger.png?image=c_crop,h_103,w_103,x_9,y_9/q_auto,f_png,w_48&v=1669867001194",
			"https://opgg-static.akamaized.net/meta/images/lol/champion/Ahri.png?image=c_crop,h_103,w_103,x_9,y_9/q_auto,f_png,w_48&v=1669867001194"
		]
	},
	{
		"rank": "46",
		"img": "https://opgg-static.akamaized.net/meta/images/lol/champion/Leblanc.png?image=c_crop,h_103,w_103,x_9,y_9/q_auto,f_png,w_64&v=1669867001194",
		"name": "르블랑",
		"tier": "5",
		"win": "47.49%",
		"pick": "3.46%",
		"ben": "6.50%",
		"hard": [
			"https://opgg-static.akamaized.net/meta/images/lol/champion/Garen.png?image=c_crop,h_103,w_103,x_9,y_9/q_auto,f_png,w_48&v=1669867001194",
			"https://opgg-static.akamaized.net/meta/images/lol/champion/Singed.png?image=c_crop,h_103,w_103,x_9,y_9/q_auto,f_png,w_48&v=1669867001194",
			"https://opgg-static.akamaized.net/meta/images/lol/champion/Renekton.png?image=c_crop,h_103,w_103,x_9,y_9/q_auto,f_png,w_48&v=1669867001194"
		]
	},
	{
		"rank": "47",
		"img": "https://opgg-static.akamaized.net/meta/images/lol/champion/Renekton.png?image=c_crop,h_103,w_103,x_9,y_9/q_auto,f_png,w_64&v=1669867001194",
		"name": "레넥톤",
		"tier": "5",
		"win": "50.38%",
		"pick": "0.73%",
		"ben": "0.46%",
		"hard": [
			"https://opgg-static.akamaized.net/meta/images/lol/champion/Zoe.png?image=c_crop,h_103,w_103,x_9,y_9/q_auto,f_png,w_48&v=1669867001194",
			"https://opgg-static.akamaized.net/meta/images/lol/champion/Anivia.png?image=c_crop,h_103,w_103,x_9,y_9/q_auto,f_png,w_48&v=1669867001194",
			"https://opgg-static.akamaized.net/meta/images/lol/champion/Akshan.png?image=c_crop,h_103,w_103,x_9,y_9/q_auto,f_png,w_48&v=1669867001194"
		]
	},
	{
		"rank": "48",
		"img": "https://opgg-static.akamaized.net/meta/images/lol/champion/Ziggs.png?image=c_crop,h_103,w_103,x_9,y_9/q_auto,f_png,w_64&v=1669867001194",
		"name": "직스",
		"tier": "5",
		"win": "49.44%",
		"pick": "1.11%",
		"ben": "0.08%",
		"hard": [
			"https://opgg-static.akamaized.net/meta/images/lol/champion/AurelionSol.png?image=c_crop,h_103,w_103,x_9,y_9/q_auto,f_png,w_48&v=1669867001194",
			"https://opgg-static.akamaized.net/meta/images/lol/champion/Heimerdinger.png?image=c_crop,h_103,w_103,x_9,y_9/q_auto,f_png,w_48&v=1669867001194",
			"https://opgg-static.akamaized.net/meta/images/lol/champion/Tryndamere.png?image=c_crop,h_103,w_103,x_9,y_9/q_auto,f_png,w_48&v=1669867001194"
		]
	},
	{
		"rank": "49",
		"img": "https://opgg-static.akamaized.net/meta/images/lol/champion/AurelionSol.png?image=c_crop,h_103,w_103,x_9,y_9/q_auto,f_png,w_64&v=1669867001194",
		"name": "아우렐리온 솔",
		"tier": "5",
		"win": "50.71%",
		"pick": "0.58%",
		"ben": "0.15%",
		"hard": [
			"https://opgg-static.akamaized.net/meta/images/lol/champion/Fizz.png?image=c_crop,h_103,w_103,x_9,y_9/q_auto,f_png,w_48&v=1669867001194",
			"https://opgg-static.akamaized.net/meta/images/lol/champion/Xerath.png?image=c_crop,h_103,w_103,x_9,y_9/q_auto,f_png,w_48&v=1669867001194",
			"https://opgg-static.akamaized.net/meta/images/lol/champion/Gangplank.png?image=c_crop,h_103,w_103,x_9,y_9/q_auto,f_png,w_48&v=1669867001194"
		]
	},
	{
		"rank": "50",
		"img": "https://opgg-static.akamaized.net/meta/images/lol/champion/Brand.png?image=c_crop,h_103,w_103,x_9,y_9/q_auto,f_png,w_64&v=1669867001194",
		"name": "브랜드",
		"tier": "5",
		"win": "50.41%",
		"pick": "0.63%",
		"ben": "0.22%",
		"hard": [
			"https://opgg-static.akamaized.net/meta/images/lol/champion/Annie.png?image=c_crop,h_103,w_103,x_9,y_9/q_auto,f_png,w_48&v=1669867001194",
			"https://opgg-static.akamaized.net/meta/images/lol/champion/Fizz.png?image=c_crop,h_103,w_103,x_9,y_9/q_auto,f_png,w_48&v=1669867001194",
			"https://opgg-static.akamaized.net/meta/images/lol/champion/Sett.png?image=c_crop,h_103,w_103,x_9,y_9/q_auto,f_png,w_48&v=1669867001194"
		]
	},
	{
		"rank": "51",
		"img": "https://opgg-static.akamaized.net/meta/images/lol/champion/Varus.png?image=c_crop,h_103,w_103,x_9,y_9/q_auto,f_png,w_64&v=1669867001194",
		"name": "바루스",
		"tier": "5",
		"win": "47.40%",
		"pick": "2.63%",
		"ben": "0.86%",
		"hard": [
			"https://opgg-static.akamaized.net/meta/images/lol/champion/Malphite.png?image=c_crop,h_103,w_103,x_9,y_9/q_auto,f_png,w_48&v=1669867001194",
			"https://opgg-static.akamaized.net/meta/images/lol/champion/Pantheon.png?image=c_crop,h_103,w_103,x_9,y_9/q_auto,f_png,w_48&v=1669867001194",
			"https://opgg-static.akamaized.net/meta/images/lol/champion/Orianna.png?image=c_crop,h_103,w_103,x_9,y_9/q_auto,f_png,w_48&v=1669867001194"
		]
	},
	{
		"rank": "52",
		"img": "https://opgg-static.akamaized.net/meta/images/lol/champion/Taliyah.png?image=c_crop,h_103,w_103,x_9,y_9/q_auto,f_png,w_64&v=1669867001194",
		"name": "탈리야",
		"tier": "5",
		"win": "49.57%",
		"pick": "0.91%",
		"ben": "0.24%",
		"hard": [
			"https://opgg-static.akamaized.net/meta/images/lol/champion/Singed.png?image=c_crop,h_103,w_103,x_9,y_9/q_auto,f_png,w_48&v=1669867001194",
			"https://opgg-static.akamaized.net/meta/images/lol/champion/Velkoz.png?image=c_crop,h_103,w_103,x_9,y_9/q_auto,f_png,w_48&v=1669867001194",
			"https://opgg-static.akamaized.net/meta/images/lol/champion/TwistedFate.png?image=c_crop,h_103,w_103,x_9,y_9/q_auto,f_png,w_48&v=1669867001194"
		]
	},
	{
		"rank": "53",
		"img": "https://opgg-static.akamaized.net/meta/images/lol/champion/Ryze.png?image=c_crop,h_103,w_103,x_9,y_9/q_auto,f_png,w_64&v=1669867001194",
		"name": "라이즈",
		"tier": "5",
		"win": "45.54%",
		"pick": "5.35%",
		"ben": "0.47%",
		"hard": [
			"https://opgg-static.akamaized.net/meta/images/lol/champion/Brand.png?image=c_crop,h_103,w_103,x_9,y_9/q_auto,f_png,w_48&v=1669867001194",
			"https://opgg-static.akamaized.net/meta/images/lol/champion/Anivia.png?image=c_crop,h_103,w_103,x_9,y_9/q_auto,f_png,w_48&v=1669867001194",
			"https://opgg-static.akamaized.net/meta/images/lol/champion/AurelionSol.png?image=c_crop,h_103,w_103,x_9,y_9/q_auto,f_png,w_48&v=1669867001194"
		]
	},
	{
		"rank": "54",
		"img": "https://opgg-static.akamaized.net/meta/images/lol/champion/Corki.png?image=c_crop,h_103,w_103,x_9,y_9/q_auto,f_png,w_64&v=1669867001194",
		"name": "코르키",
		"tier": "5",
		"win": "48.12%",
		"pick": "1.37%",
		"ben": "0.16%",
		"hard": [
			"https://opgg-static.akamaized.net/meta/images/lol/champion/Garen.png?image=c_crop,h_103,w_103,x_9,y_9/q_auto,f_png,w_48&v=1669867001194",
			"https://opgg-static.akamaized.net/meta/images/lol/champion/Velkoz.png?image=c_crop,h_103,w_103,x_9,y_9/q_auto,f_png,w_48&v=1669867001194",
			"https://opgg-static.akamaized.net/meta/images/lol/champion/Xerath.png?image=c_crop,h_103,w_103,x_9,y_9/q_auto,f_png,w_48&v=1669867001194"
		]
	},
	{
		"rank": "55",
		"img": "https://opgg-static.akamaized.net/meta/images/lol/champion/Azir.png?image=c_crop,h_103,w_103,x_9,y_9/q_auto,f_png,w_64&v=1669867001194",
		"name": "아지르",
		"tier": "5",
		"win": "45.96%",
		"pick": "3.06%",
		"ben": "0.74%",
		"hard": [
			"https://opgg-static.akamaized.net/meta/images/lol/champion/Velkoz.png?image=c_crop,h_103,w_103,x_9,y_9/q_auto,f_png,w_48&v=1669867001194",
			"https://opgg-static.akamaized.net/meta/images/lol/champion/Tristana.png?image=c_crop,h_103,w_103,x_9,y_9/q_auto,f_png,w_48&v=1669867001194",
			"https://opgg-static.akamaized.net/meta/images/lol/champion/Brand.png?image=c_crop,h_103,w_103,x_9,y_9/q_auto,f_png,w_48&v=1669867001194"
		]
	},
	{
		"rank": "56",
		"img": "https://opgg-static.akamaized.net/meta/images/lol/champion/Jayce.png?image=c_crop,h_103,w_103,x_9,y_9/q_auto,f_png,w_64&v=1669867001194",
		"name": "제이스",
		"tier": "5",
		"win": "49.03%",
		"pick": "0.54%",
		"ben": "0.07%",
		"hard": [
			"https://opgg-static.akamaized.net/meta/images/lol/champion/Rumble.png?image=c_crop,h_103,w_103,x_9,y_9/q_auto,f_png,w_48&v=1669867001194",
			"https://opgg-static.akamaized.net/meta/images/lol/champion/Cassiopeia.png?image=c_crop,h_103,w_103,x_9,y_9/q_auto,f_png,w_48&v=1669867001194",
			"https://opgg-static.akamaized.net/meta/images/lol/champion/Pantheon.png?image=c_crop,h_103,w_103,x_9,y_9/q_auto,f_png,w_48&v=1669867001194"
		]
	},
	{
		"rank": "57",
		"img": "https://opgg-static.akamaized.net/meta/images/lol/champion/Malphite.png?image=c_crop,h_103,w_103,x_9,y_9/q_auto,f_png,w_64&v=1669867001194",
		"name": "말파이트",
		"tier": "5",
		"win": "48.78%",
		"pick": "0.53%",
		"ben": "0.42%",
		"hard": [
			"https://opgg-static.akamaized.net/meta/images/lol/champion/Galio.png?image=c_crop,h_103,w_103,x_9,y_9/q_auto,f_png,w_48&v=1669867001194",
			"https://opgg-static.akamaized.net/meta/images/lol/champion/Anivia.png?image=c_crop,h_103,w_103,x_9,y_9/q_auto,f_png,w_48&v=1669867001194",
			"https://opgg-static.akamaized.net/meta/images/lol/champion/Lux.png?image=c_crop,h_103,w_103,x_9,y_9/q_auto,f_png,w_48&v=1669867001194"
		]
	},
	{
		"rank": "58",
		"img": "https://opgg-static.akamaized.net/meta/images/lol/champion/Chogath.png?image=c_crop,h_103,w_103,x_9,y_9/q_auto,f_png,w_64&v=1669867001194",
		"name": "초가스",
		"tier": "5",
		"win": "47.93%",
		"pick": "0.60%",
		"ben": "0.20%",
		"hard": [
			"https://opgg-static.akamaized.net/meta/images/lol/champion/Gangplank.png?image=c_crop,h_103,w_103,x_9,y_9/q_auto,f_png,w_48&v=1669867001194",
			"https://opgg-static.akamaized.net/meta/images/lol/champion/Taliyah.png?image=c_crop,h_103,w_103,x_9,y_9/q_auto,f_png,w_48&v=1669867001194",
			"https://opgg-static.akamaized.net/meta/images/lol/champion/Velkoz.png?image=c_crop,h_103,w_103,x_9,y_9/q_auto,f_png,w_48&v=1669867001194"
		]
	}
]